LICENSE
README.md
setup.cfg
setup.py
AshLogger/AshLogger.py
AshLogger/__init__.py
AshLogger.egg-info/PKG-INFO
AshLogger.egg-info/SOURCES.txt
AshLogger.egg-info/dependency_links.txt
AshLogger.egg-info/top_level.txt