Metadata-Version: 2.1
Name: AshLogger
Version: 0.5
Summary: Hassle free ready to use out of the box Python3 logger.
Home-page: https://github.com/ashfaque/AshLogger
Download-URL: https://github.com/ashfaque/AshLogger/archive/refs/tags/v_05.tar.gz
Author: Ashfaque Alam
Author-email: ashfaquealam496@yahoo.com
License: GNU GPLv3
Keywords: ASHFAQUE,ASHFAQUE ALAM,PYTHON,LOGGER,PYTHON LOGGER
Classifier: Development Status :: 5 - Production/Stable
Classifier: Intended Audience :: Developers
Classifier: Topic :: Software Development :: Build Tools
Classifier: Topic :: Software Development :: Libraries :: Python Modules
Classifier: License :: OSI Approved :: GNU General Public License (GPL)
Classifier: Operating System :: OS Independent
Classifier: Programming Language :: Python :: 3
Classifier: Programming Language :: Python :: 3 :: Only
Classifier: Programming Language :: Python :: 3.5
Classifier: Programming Language :: Python :: 3.6
Classifier: Programming Language :: Python :: 3.7
Classifier: Programming Language :: Python :: 3.8
Classifier: Programming Language :: Python :: 3.9
Classifier: Programming Language :: Python :: 3.10
Classifier: Programming Language :: Python :: 3.11
Classifier: Programming Language :: Python :: 3.12
Requires-Python: >=3.5
License-File: LICENSE
